sambanova_gradio/__init__.py
sambanova_gradio-0.1.9.dist-info/METADATA
sambanova_gradio-0.1.9.dist-info/WHEEL
sambanova_gradio-0.1.9.dist-info/licenses/LICENSE
sambanova_gradio-0.1.9.dist-info/RECORD
