Metadata-Version: 2.3
Name: sambanova-gradio
Version: 0.1.9
Summary: A Python package for replicating Gradio applications
Project-URL: homepage, https://github.com/gradio-app/sambanova-gradio
Project-URL: repository, https://github.com/gradio-app/sambanova-gradio
Author-email: Kaizhao Liang <kaizhao.liang@sambanovasystems.com>
License-File: LICENSE
Classifier: License :: OSI Approved :: MIT License
Classifier: Operating System :: OS Independent
Classifier: Programming Language :: Python :: 3
Requires-Python: >=3.10
Requires-Dist: gradio>=5.4.0
Requires-Dist: openai
Provides-Extra: dev
Requires-Dist: pytest; extra == 'dev'
